vendor_grab/__init__.py
vendor_grab/_version.py
vendor_grab/vendor_grab.py
vendor_grab-0.0.2.dist-info/METADATA
vendor_grab-0.0.2.dist-info/WHEEL
vendor_grab-0.0.2.dist-info/entry_points.txt
vendor_grab-0.0.2.dist-info/licenses/LICENSE
vendor_grab-0.0.2.dist-info/RECORD
