Metadata-Version: 2.4
Name: vendor_grab
Version: 0.0.2
Summary: Grab files from a vendor tar file.
Project-URL: Homepage, https://sr.ht/~jkenlooper/vendor-grab/
Project-URL: documentation, https://git.sr.ht/~jkenlooper/vendor-grab/tree/main/item/README.md
Project-URL: repository, https://git.sr.ht/~jkenlooper/vendor-grab
Project-URL: changelog, https://git.sr.ht/~jkenlooper/vendor-grab/tree/main/item/CHANGELOG.md
Project-URL: Tracker, https://todo.sr.ht/~jkenlooper/vendor-grab
Author-email: Jake Hickenlooper <jake@weboftomorrow.com>
License: ISCL
License-File: LICENSE
Classifier: Development Status :: 3 - Alpha
Classifier: Environment :: Console
Classifier: Intended Audience :: Developers
Classifier: License :: OSI Approved :: ISC License (ISCL)
Classifier: Natural Language :: English
Classifier: Operating System :: OS Independent
Classifier: Operating System :: POSIX
Classifier: Programming Language :: Python :: 3.9
Classifier: Programming Language :: Python :: 3.10
Classifier: Programming Language :: Python :: 3.11
Classifier: Programming Language :: Python :: 3.12
Classifier: Topic :: Internet :: WWW/HTTP :: Site Management
Classifier: Topic :: Software Development :: Build Tools
Requires-Python: <4,>=3.9
Requires-Dist: tomli>=1.1.0; python_version < '3.11'
Provides-Extra: cli
Provides-Extra: dev
Provides-Extra: test
Requires-Dist: coverage; extra == 'test'
Requires-Dist: pytest; extra == 'test'
